{"id": "macrocycle_f9caad7f", "source": "train_generation.pdf", "type": "macrocycle_rule", "applies_to": "structuration", "inputs": [], "outputs": [], "conditions": {}, "rule_text": "a) Dur√©e totale cible : macro-cycles\n‚óè Par d√©faut : 1 an\n‚óè Alternative : entre [6 mois-1an]\nBut : d√©finir l‚Äôhorizon de progression pour r√©partir les cycles", "structured": {"muscle_groups_required": [], "muscle_groups_optional": [], "exercise_families_allowed": [], "equipment_required": [], "equipment_optional": [], "intensity_range": null, "volume_range": null, "rest_range": null, "balance_required": false, "antagonist_pairs": [], "variety_required": false}, "keywords": ["macrocycle", "dur√©e totale cible", "1 an", "6 mois-1an", "horizon de progression", "cycles"], "conditions_parsed": {"applies_when": "dur√©e totale cible est d√©finie", "exceptions": null}}
{"id": "mesocycle_9e3ef09e", "source": "train_generation.pdf", "type": "mesocycle_rule", "applies_to": "structuration", "inputs": [], "outputs": [], "conditions": {}, "rule_text": "b) D√©coupage en m√©so-cycles\n‚óè Chaque m√©so-cycle dure 2 √† 3 mois\n‚óè Nombre total : 3 prolongeable en 4 selon la dur√©e du programme\n‚óè Fonction : chaque macrocycle cible un objectif √©volutif ou une\ncomp√©tence dominante\nR√©partition :\n6/7 mois -> 3 cycles de 2 mois ;\n8 mois -> 4 cycles de 2 mois ;\n9 mois -> 3 cycles de 3 mois ;\n10/11 mois -> 4 macro cycles de 2 mois et demi ;\n12 mois -> 4 cycles de 3 mois ;\nsous onglet macro", "structured": {"muscle_groups_required": [], "muscle_groups_optional": [], "exercise_families_allowed": [], "equipment_required": [], "equipment_optional": [], "intensity_range": null, "volume_range": null, "rest_range": null, "balance_required": false, "antagonist_pairs": [], "variety_required": false}, "keywords": ["m√©so-cycle", "dur√©e", "objectif √©volutif", "comp√©tence dominante", "r√©partition", "macrocycle"], "conditions_parsed": {"applies_when": "dur√©e du programme", "exceptions": null}}
{"id": "microcycle_c3f20258", "source": "train_generation.pdf", "type": "microcycle_rule", "applies_to": "structuration", "inputs": [], "outputs": [], "conditions": {}, "rule_text": "c) Surd√©coupage en micro-cycles\n‚óè Un micro-cycles = 2 √† 3 semaines\n‚óè Permet de varier l‚Äôentra√Ænement, les exercices et les formats tout en\ngardant la coh√©rence du macrocycle\n‚óè √âvite la lassitude, favorise la progression\n‚óè Nom du micro-cycle : (ex. ‚ÄúProgression technique & prise en main‚Äù)\nDur√©e : 2 √† 3 semaines\n‚óè Focus :\n‚óã Mouvements : (ex. polyarticulaires / mobilit√© / cardio HIIT)\nFormat : (ex. circuits / split haut-bas / full body / tempo /\nAMRAP‚Ä¶)\n‚óã Charge : (ex. mod√©r√©e / progressive / en mont√©e)\n‚óè Objectif du cycle : (ex. consolider les bases techniques, augmenter\nl‚Äôintensit√©, stimuler un nouveau seuil, tester une variation de format,\nintroduire un nouveau tempo‚Ä¶)\nüìÖ", "structured": {"muscle_groups_required": [], "muscle_groups_optional": [], "exercise_families_allowed": ["polyarticulaires", "mobilit√©", "cardio HIIT", "circuits", "split haut-bas", "full body", "tempo", "AMRAP"], "equipment_required": [], "equipment_optional": [], "intensity_range": null, "volume_range": null, "rest_range": null, "balance_required": false, "antagonist_pairs": [], "variety_required": true}, "keywords": ["surd√©coupage", "micro-cycles", "variation", "coh√©rence", "lassitude", "progression", "nom du micro-cycle", "dur√©e", "focus", "mouvements", "format", "charge", "objectif du cycle"], "conditions_parsed": {"applies_when": "sur le surd√©coupage en micro-cycles", "exceptions": null}}
{"id": "weekly_split_ae8335df", "source": "train_generation.pdf", "type": "weekly_split_rule", "applies_to": "weekly_planning", "inputs": ["nombre_de_sessions_par_semaine", "niveau_sportif", "objectif_principal"], "outputs": ["split", "temps_par_seance"], "conditions": {}, "rule_text": "üìÖ\n3. R√©partition des s√©ances dans la semaine\nCoach Mike doit ensuite planifier :\n‚óè Combien de s√©ances par semaine l‚Äôutilisateur peut faire (1, 2, 3, 4 ou\n+) (3 d√©faut)\n‚óè En fonction du volume, il d√©termine :\n‚óã Le split (full body, haut/bas, cardio, mobilit√©‚Ä¶)\n‚óã La r√©partition √©quilibr√©e pour chaque micro-cycle\n‚óã Le temps par s√©ance (environ : 30 min ; 45 min ; 1h selon le\nniveau) (par d√©faut selon le niveau)\nExemples :\n‚óè 1 s√©ance : full body complet : s√©ance dense multi-objectifs\n‚óè 2 s√©ances : full body/cardio : Alternance effort global / r√©cup√©ration\nactive (ou full body/cardio *2)\n‚óè 3 s√©ances : haut + bas + cardio/full body : split mod√©r√© avec vari√©t√©\n‚óè 4 s√©ances : haut + bas + full body/cardio + full body/core : approche\nstructur√©e avec √©quilibre\n‚óè 5-6 s√©ances : split complet avec sp√©cifique bras : intensification\nprogressive + logique de rotation\n-mobilit√© √† chaque s√©ance (√©chauffement)\n-doubler haut/bas pour de la prise musculaire/gain de force √† partir de 3\ns√©ances\n(int√©grer le cardio dans les s√©ances, plus efficace pour perdre du poids)\nLe coach veille √† :\n‚óè Varier les blocs et formats d‚Äôune semaine √† l‚Äôautre (s√©ances ludiques /\ntechniques / cardio / r√©cup√©ration active)\n‚óè Maintenir une coh√©rence de charge (volume √ó intensit√© √ó r√©cup)\n‚óè √âviter 2 s√©ances intenses cons√©cutives", "structured": {"muscle_groups_required": ["haut", "bas", "core"], "muscle_groups_optional": ["bras"], "exercise_families_allowed": ["full body", "cardio", "mobilit√©"], "equipment_required": [], "equipment_optional": [], "intensity_range": null, "volume_range": "1-6 s√©ances", "rest_range": null, "balance_required": true, "antagonist_pairs": [["haut", "bas"]], "variety_required": true}, "keywords": ["r√©partition", "s√©ances", "volume", "split", "√©quilibre", "mobilit√©", "vari√©t√©", "coh√©rence", "intensit√©"], "conditions_parsed": {"applies_when": "Coach Mike planifie les s√©ances selon le volume et le split", "exceptions": "√âviter 2 s√©ances intenses cons√©cutives"}}
{"id": "session_blocks_6f026fba", "source": "train_generation.pdf", "type": "session_block_rule", "applies_to": "session_construction", "inputs": ["niveau_sportif"], "outputs": ["structure_seance"], "conditions": {}, "rule_text": "üß© 4. Construction des s√©ances (blocs p√©dagogiques)\nChaque s√©ance est compos√©e de blocs modulaires. Leur contenu d√©pend\ndu niveau de l‚Äôutilisateur :\nBlocs typiques :\n‚óè Introduction mentale (focus, intention du jour)\n‚óè √âchauffement g√©n√©ral (cardio, mobilit√© articulaire)\nActivation sp√©cifique (gainage, pr√©-fatigue, √©chauffement technique‚Ä¶)\n‚óè Corps de s√©ance (3 √† 6 exercices selon le niveau)\n‚óè Retour au calme (respiration, √©tirements, automassages)\n‚óè Message de cl√¥ture (motivation, teaser prochaine s√©ance)\nPour chaque niveau (d√©butant ‚Üí avanc√©), on adapte :\n‚óè Le nombre de blocs\n‚óè La dur√©e de la s√©ance\n‚óè Le type de format (circuit, superset, AMRAP, tempo, etc.)\n‚óè Le niveau de consignes (plus ou moins d√©taill√©es)\n-prendre en compte le retour sur l‚Äô√©chelle de fatigue et l‚Äôappr√©ciation pour les\nfutures s√©ances", "structured": {"muscle_groups_required": [], "muscle_groups_optional": [], "exercise_families_allowed": ["gainage", "√©chauffement technique", "exercices de corps de s√©ance"], "equipment_required": [], "equipment_optional": [], "intensity_range": null, "volume_range": "3-6 exercices selon le niveau", "rest_range": null, "balance_required": false, "antagonist_pairs": [], "variety_required": true}, "keywords": ["blocs modulaires", "niveau de l‚Äôutilisateur", "introduction mentale", "√©chauffement g√©n√©ral", "corps de s√©ance", "retour au calme", "message de cl√¥ture", "adaptation", "dur√©e de la s√©ance", "type de format", "niveau de consignes", "√©chelle de fatigue"], "conditions_parsed": {"applies_when": "selon le niveau de l‚Äôutilisateur", "exceptions": null}}
{"id": "exercise_choice_e3440e7f", "source": "train_generation.pdf", "type": "exercise_choice_rule", "applies_to": "exercise_selection", "inputs": ["objectif_principal", "zone_musculaire"], "outputs": ["type_exercice"], "conditions": {}, "rule_text": "üß† 5. Choix des exercices (selon objectif)\nChaque format de travail (/objectif) am√®ne un focus sp√©cifique :\nmacro to micro (dans les exos)\njouer sur l‚Äôangulation, le mat√©riel\nhaut : pectoraux, delto√Ødes, muscles du dos (trap√®zes, grand dorsal,\nrhombo√Øde,...)\nbras : biceps, triceps, brachial ant√©rieur\nbas : quadriceps, ischio, mollets, adducteurs/abducteurs, fessiers\ncore : transverses, grand droit abdomen, obliques, lombaires\nPerte de poids : full body + cardio, r√©cup√©ration r√©duite (exos polyarticulaires\n: traction, squat, dips‚Ä¶)\nPrise de masse : hypertrophie, tempo lent, charges progressives\nMobilit√©/souplesse : mouvements amples, fluides, √©tirements\ndynamiques/statique\nR√©duction du stress : lenteur, respiration, ambiance calme\nPerformance : puissance, technique, exercices avanc√©s\nSant√© globale : vari√©t√© √©quilibr√©e, mouvements fonctionnels", "structured": {"muscle_groups_required": ["pectoraux", "delto√Ødes", "muscles du dos", "biceps", "triceps", "brachial ant√©rieur", "quadriceps", "ischio", "mollets", "adducteurs", "abducteurs", "fessiers", "transverses", "grand droit abdomen", "obliques", "lombaires"], "muscle_groups_optional": [], "exercise_families_allowed": ["polyarticulaires", "traction", "squat", "dips"], "equipment_required": [], "equipment_optional": [], "intensity_range": null, "volume_range": null, "rest_range": null, "balance_required": true, "antagonist_pairs": [["biceps", "triceps"], ["pectoraux", "dos"], ["quadriceps", "ischio"]], "variety_required": true}, "keywords": ["choix des exercices", "objectif", "macro to micro", "angulation", "mat√©riel", "perte de poids", "prise de masse", "mobilit√©", "souplesse", "r√©duction du stress", "performance", "sant√© globale"], "conditions_parsed": {"applies_when": "selon objectif", "exceptions": null}}
{"id": "equipment_ef806df7", "source": "train_generation.pdf", "type": "equipment_rule", "applies_to": "exercise_selection", "inputs": ["materiel_disponible"], "outputs": ["type_exercice"], "conditions": {}, "rule_text": "üõ† 6. Adaptation au mat√©riel MVP2\nSelon le mat√©riel, on ajuste automatiquement :\n‚óè Poids du corps seul : focus bodyweight, adaptations simplifi√©es\n‚óè √âlastiques : r√©sistance modulable, travail en contr√¥le\n‚óè Poids libres : exos en charge, tempo lent\n‚óè Mat√©riel complet : vari√©t√© maximale, splits, formats riches", "structured": {"muscle_groups_required": [], "muscle_groups_optional": [], "exercise_families_allowed": [], "equipment_required": ["Poids du corps", "√âlastiques", "Poids libres", "Mat√©riel complet"], "equipment_optional": [], "intensity_range": null, "volume_range": null, "rest_range": null, "balance_required": false, "antagonist_pairs": [], "variety_required": true}, "keywords": ["adaptation", "mat√©riel", "bodyweight", "√©lastiques", "poids libres", "mat√©riel complet", "vari√©t√©", "r√©sistance modulable", "travail en contr√¥le", "tempo lent"], "conditions_parsed": {"applies_when": "selon le mat√©riel", "exceptions": null}}
{"id": "output_format_df530470", "source": "train_generation.pdf", "type": "output_format_rule", "applies_to": "output_format", "inputs": [], "outputs": ["texte_seance"], "conditions": {}, "rule_text": "üìÑ 7. Format de sortie MVP\nEn MVP0, Coach Mike g√©n√®re un texte simple pour chaque s√©ance :\n‚óè Un titre (ex: ‚ÄúS√©ance 2 ‚Äì Haut du corps & cardio‚Äù)\n‚óè Une intro adapt√©e au profil (motivation ou focus)\n‚óè La liste des exos pour l‚Äô√©chauffement (nom + dur√©e)\n‚óè Les exos principaux (nom + reps/s√©ries + consigne simple dont crit√®res\nposture et conseils s√©curit√©)\n‚óè Le retour au calme (√©tirements, respiration guid√©e)\n‚óè Une phrase de cl√¥ture personnalis√©e", "structured": {"muscle_groups_required": [], "muscle_groups_optional": [], "exercise_families_allowed": [], "equipment_required": [], "equipment_optional": [], "intensity_range": null, "volume_range": null, "rest_range": null, "balance_required": false, "antagonist_pairs": [], "variety_required": false}, "keywords": ["MVP0", "Coach Mike", "texte simple", "s√©ance", "titre", "intro", "profil", "motivation", "focus", "exos", "√©chauffement", "exos principaux", "retour au calme", "√©tirements", "respiration guid√©e", "phrase de cl√¥ture personnalis√©e"], "conditions_parsed": {"applies_when": null, "exceptions": null}}
